{
    "testimonialData":[
        {
            "name": "Sarah Thompson",
            "star": 4,
            "image": "https://i.ibb.co/zhHwwr2/dado.jpg",
            "title": " Excellent Quality and Service!",
            "review": "I recently purchased a mechanical keyboard from this shop, and I'm thoroughly impressed! The build quality is outstanding, and the switches feel incredibly smooth. Customer service was top-notch, helping me choose the perfect keyboard for my needs.",
            "designation": "CEO",
            "company": "Extream"
        },

        {
            "name": "John Davis",
            "star": 5,
            "image": "https://i.ibb.co/1b6mJVQ/hridoy.jpg",
            "title": "Great Selection and Prices",
            "review": "This shop has a fantastic selection of keyboards, from budget-friendly options to high-end models. I found exactly what I was looking for at a great price. The website is easy to navigate, and the checkout process was seamless. ",
            "designation": "Founder",
            "company": "Acme Corporation"
        },
        {
            "name": "Michael Brown",
            "star": 5,
            "image": "https://i.ibb.co/kQfsxfK/images.jpg",
            "title": "Excellent Customer Support",
            "review": "I had an issue with one of the keys on my new keyboard, and the customer support team was amazing. They quickly resolved my problem and sent a replacement part without any hassle. The keyboard itself is fantastic, with a great tactile feel and sleek design. ",
            "designation": "Globex Corporation",
            "company": "Acme Corporation"
        },
        {
            "name": "Emily Roberts",
            "star": 5,
            "image": "https://i.ibb.co/8P1Vrw9/emily.png",
            "title": "Excellent Customer Support",
            "review": "If you're into custom keyboards, this is the place to go! I ordered a custom-built keyboard, and the team here was incredibly helpful throughout the process. The end product is exactly what I envisioned and performs beautifully.",
            "designation": "Web Developer",
            "company": "Initech"
        },
        {
            "name": "Sarah Thompson",
            "star": 4,
            "image": "https://i.ibb.co/zhHwwr2/dado.jpg",
            "title": " Excellent Quality and Service!",
            "review": "I recently purchased a mechanical keyboard from this shop, and I'm thoroughly impressed! The build quality is outstanding, and the switches feel incredibly smooth. Customer service was top-notch, helping me choose the perfect keyboard for my needs.",
            "designation": "CEO",
            "company": "Extream"
        },
        {
            "name": "John Davis",
            "star": 5,
            "image": "https://i.ibb.co/1b6mJVQ/hridoy.jpg",
            "title": "Great Selection and Prices",
            "review": "This shop has a fantastic selection of keyboards, from budget-friendly options to high-end models. I found exactly what I was looking for at a great price. The website is easy to navigate, and the checkout process was seamless. ",
            "designation": "Founder",
            "company": "Acme Corporation"
        }
    ]
}